ascimage/__init__.py
ascimage-0.0.1.dist-info/LICENSE
ascimage-0.0.1.dist-info/METADATA
ascimage-0.0.1.dist-info/WHEEL
ascimage-0.0.1.dist-info/entry_points.txt
ascimage-0.0.1.dist-info/top_level.txt
ascimage-0.0.1.dist-info/RECORD
