Metadata-Version: 2.1
Name: ascimage
Version: 0.0.1
Summary: imageprint with asciii code.
Home-page: UNKNOWN
Author: fallnjump
Author-email: tfjsm.app@gmail.com
License: LICENSE
Platform: UNKNOWN
Requires-Dist: numpy
